my_package/SportMatchManager.py
my_package/__init__.py
my_package/match.py
my_package/player.py
my_package/score_event.py
my_package/team.py
sportmanagement-0.1.0.dist-info/METADATA
sportmanagement-0.1.0.dist-info/WHEEL
sportmanagement-0.1.0.dist-info/top_level.txt
sportmanagement-0.1.0.dist-info/RECORD
