Metadata-Version: 2.4
Name: sportManagement
Version: 0.1.0
Summary: a stupid and impractical sport managing package, dont download it lol
Author: Aaron Ethan
Author-email: AaronOriginal2009@gmail.com
Classifier: Programming Language :: Python :: 3
Classifier: Operating System :: OS Independent
Requires-Python: >=3.7
Dynamic: author
Dynamic: author-email
Dynamic: classifier
Dynamic: requires-python
Dynamic: summary
